killallappsinfolder/README.MD
killallappsinfolder/__init__.py
killallappsinfolder/requirements.txt
killallappsinfolder/thirdparty.json
killallappsinfolder-0.10.dist-info/LICENSE.rst
killallappsinfolder-0.10.dist-info/METADATA
killallappsinfolder-0.10.dist-info/WHEEL
killallappsinfolder-0.10.dist-info/top_level.txt
killallappsinfolder-0.10.dist-info/RECORD
